{
    "CCCCGG": {
        "AnchoredIrrCount": 29,
        "IrrPairCount": 369,
        "RegionsWithIrrAnchors": {
            "9:27572955-27573817": 29
        },
        "RegionsWithIrrs": {
            "11:2906070-2906079": 47,
            "11:44748597-44748604": 4,
            "2:240659823-240659838": 42,
            "5:176798059-176798060": 5,
            "X:153569934-153569936": 56,
            "X:153618844-153618848": 48,
            "X:53652751-53652771": 565
        },
        "RepeatUnit": "CCCCGG"
    },
    "Depth": 4.33381310946798e-05,
    "ReadLength": 150
}
